love_ai/__init__.py
love_ai/__main__.py
love_ai/config.py
love_ai/core.py
love_ai/persistence.py
love_ai/adapters/fs.py
love_ai/adapters/sentiment.py
love_ai-1.2.0.dist-info/METADATA
love_ai-1.2.0.dist-info/WHEEL
love_ai-1.2.0.dist-info/licenses/LICENSE
love_ai-1.2.0.dist-info/RECORD
