Metadata-Version: 2.4
Name: love-ai
Version: 1.2.0
Summary: Learnable Object Valuation Engine - Ethical governance system for computational decisions
Project-URL: Homepage, https://github.com/love-ai-engine/love-ai
Project-URL: Documentation, https://github.com/love-ai-engine/love-ai/blob/main/LOVE%20IS%20ALL%20YOU%20NEED.md
Project-URL: Repository, https://github.com/love-ai-engine/love-ai
Project-URL: Bug Tracker, https://github.com/love-ai-engine/love-ai/issues
Author-email: Jorge Checa Jaspe <engine.ops.love@gmail.com>
License: AGPL-3.0
License-File: LICENSE
Keywords: ai,decision-making,ethics,governance,protection
Classifier: Development Status :: 4 - Beta
Classifier: Intended Audience :: Developers
Classifier: License :: OSI Approved :: GNU Affero General Public License v3 or later (AGPLv3+)
Classifier: Programming Language :: Python :: 3
Classifier: Programming Language :: Python :: 3.7
Classifier: Programming Language :: Python :: 3.8
Classifier: Programming Language :: Python :: 3.9
Classifier: Programming Language :: Python :: 3.10
Classifier: Programming Language :: Python :: 3.11
Classifier: Topic :: Scientific/Engineering :: Artificial Intelligence
Classifier: Topic :: Software Development :: Libraries :: Python Modules
Requires-Python: >=3.7
Provides-Extra: api
Requires-Dist: google-generativeai>=0.3.0; extra == 'api'
Provides-Extra: dev
Requires-Dist: black>=22.0; extra == 'dev'
Requires-Dist: flake8>=5.0; extra == 'dev'
Requires-Dist: mypy>=0.990; extra == 'dev'
Requires-Dist: pytest-cov>=4.0; extra == 'dev'
Requires-Dist: pytest>=7.0; extra == 'dev'
